appbundler/__init__.py
appbundler/__main__.py
appbundler/__version__.py
appbundler/appbundler.py
appbundler/utils.py
appbundler-0.2.0a0.dist-info/LICENSE
appbundler-0.2.0a0.dist-info/METADATA
appbundler-0.2.0a0.dist-info/WHEEL
appbundler-0.2.0a0.dist-info/entry_points.txt
appbundler-0.2.0a0.dist-info/top_level.txt
appbundler-0.2.0a0.dist-info/RECORD
